latexdiffcite/__init__.py
latexdiffcite/__main__.py
latexdiffcite/latexdiffcite.py
latexdiffcite-1.0.6.dist-info/DESCRIPTION.rst
latexdiffcite-1.0.6.dist-info/METADATA
latexdiffcite-1.0.6.dist-info/RECORD
latexdiffcite-1.0.6.dist-info/WHEEL
latexdiffcite-1.0.6.dist-info/entry_points.txt
latexdiffcite-1.0.6.dist-info/metadata.json
latexdiffcite-1.0.6.dist-info/top_level.txt
