Metadata-Version: 2.0
Name: latexdiffcite
Version: 1.0.6
Summary: Wrapper around latexdiff to make citations diff properly
Home-page: https://github.com/cmeeren/latexdiffcite
Author: Christer van der Meeren
Author-email: cmeeren@gmail.com
License: BSD
Keywords: latex,latexdiff,citations
Platform: UNKNOWN
Classifier: Development Status :: 5 - Production/Stable
Classifier: Intended Audience :: End Users/Desktop
Classifier: License :: OSI Approved :: BSD License
Classifier: Natural Language :: English
Classifier: Operating System :: Unix
Classifier: Operating System :: Microsoft :: Windows
Classifier: Programming Language :: Python
Classifier: Programming Language :: Python :: 2
Classifier: Programming Language :: Python :: 2.7
Classifier: Programming Language :: Python :: 3
Classifier: Programming Language :: Python :: 3.3
Classifier: Programming Language :: Python :: 3.4
Classifier: Topic :: Text Processing :: Markup :: LaTeX
Classifier: Topic :: Utilities
